{
  "metadata": {
    "agent_name": "Tavily Waste Management Scraper Agent",
    "version": "1.0.0",
    "collection_date": "2025-05-12T21:14:52.327845",
    "report_count": 4,
    "sources_count": 4
  },
  "reports": [
    {
      "title": "PDF",
      "date": "Unknown",
      "url": "https://www.forumambiental.org/files/RESIDUOS/Potencial_economico_sector_residuos_en_Espana_24_Resumen-ejecutivo.pdf",
      "source": "Forumambiental.org",
      "format": "HTML",
      "content": "Diciembre 2024 Contexto: generación de residuos en España La generación total de residuos en España, considerando las diferentes tipologías, asciende a más de 115 millones de toneladas 02 Municipales 22,7 millones de toneladas (20%) Industria y servicios (incluye minería y producción de energía) 22,7 millones de toneladas (20%) Suministro de agua, saneamiento, gestión de residuos y descontaminación 26,7 millones de toneladas (23%) Agricultura, ganadería, silvicultura y pesca 6,3 millones de [...] Objetivos claves El sector de la gestión de residuos en España se enfrenta a importantes desafíos para cumplir con los ambiciosos objetivos establecidos para 2035. Aunque se han realizado progresos en algunas áreas, las previsiones no son favorables y aún persisten brechas significativas tanto en prevención, recogida separada, reciclaje y vertido.",
      "raw_content": "El potencial económico del sector de la gestión de los residuos en España.\nEste informe tiene por objetivo cuantificar la contribución y la creación de valor de las actividades de gestión de residuos a la economía española e identificar las principales áreas de desarrollo económico del sector en los próximos años.\nDiciembre 2024 Contexto: generación de residuos en España La generación total de residuos en España, considerando las diferentes tipologías, asciende a más de 115 millones de toneladas 02 Municipales 22,7 millones de toneladas (20%) Industria y servicios (incluye minería y producción de energía) 22,7 millones de toneladas (20%) Suministro de agua, saneamiento, gestión de residuos y descontaminación 26,7 millones de toneladas (23%) Agricultura, ganadería, silvicultura y pesca 6,3 millones de toneladas (5%) Residuos de construcción y demolición 37,1 millones de toneladas (32%) Ingresos, VAB y ocupación Ingresos de explotación (M€) Valor Añadido Bruto (M€) Ocupación 41.279 10.410 168.397 Contribución a la generación de riqueza económica (VAB) según tipo de residuo (procedencia) Representa un 4,9% del VAB industrial de España Residuos de la construcción 4,2% Residuos procedentes de (1) industria, (2) servicios, (3) agricultura, ganadería, silvicultura y pesca, y (4) suministro de agua, saneamiento, gestión de residuos y descontaminación. 56,5% Residuos municipales (hogares) 39,3% 03 SECTOR RESIDUOS 10.410 M € Industria química 10.992 M € Fabricación de productos metálicos 12.874 M € Fabricación de productos farmacéuticos 8.836 M € Industria de la madera, del corcho y del papel.\n6.318 M € Fabricación de material y productos electrónicos 6.560 M € Fabricación de productos de caucho y plásticos 6.960 M € Industria de la alimentación, fabricación de bebidas e industria del tabaco (25.741 M €) Agricultura, ganadería, silvicultura y pesca (33.378 M €) Construcción (62.978 M €) Fabricación de vehículos de motor y remolques 11.906 M € Industria textil 8.228 M € La rentabilidad económica del sector residuos en España se sitúa alrededor del 5,4%, en una posición comparable a industrias consolidadas como la química, textil o del papel. 04 Comparativa VAB con otros sectores de actividad Creación de ocupación El sector Residuos representa un 7,1% de la ocupación industrial de España 21% mujeres A medida que se progrese en el cumplimiento de objetivos normativos, y las actividades suban en la jerarquía de gestión de residuos, la ocupación en el sector crecerá, con actividad local y no deslocalizable.\n05 Tamaño de las empresas del sector Según el número de empresas Grandes empresas 5,0% Medianas empresas 5,9% Pequeñas empresas 89,1% ¿Qué cifra de negocio concentra cada tipo de empresa?\nGrandes empresas 43,4% Medianas empresas 25,4% Pequeñas empresas 31,2% 06 0% 50% 100% 150% 200% 250% 300% 350% 0% 50% 100% 150% 200% 250% 0% 50% 100% 150% 200% 250% INGRESOS DE EXPLOTACIÓN OCUPACIÓN VALOR AGREGADO BRUTO (VAB) 2000 2005 2010 2015 2022 2000 2005 2010 2015 2022 2000 2005 2010 2015 2022 x3,2 x2,3 x2,1 La evolución del sector en el período 2000-2022 Conclusión: El sector de los residuos no dejará de ampliar capacidades y alcance en los próximos años, ante el gran reto de cumplir con los objetivos normativos en materia de residuos y abrazar los principios de una economía circular.\n07 Objetivos clave en materia de residuos municipales Recogida separada Desde 2024, es obligatorio recoger separadamente los biorresiduos, además de las fracciones de residuos municipales ya existentes: envases, papel y cartón, y vidrio. Para 2025, se prevé la ampliación de las fracciones recogidas de manera separada, incluyendo residuos textiles, aceite de cocina usado, residuos voluminosos y residuos peligrosos. Estas medidas están orientadas a alcanzar: Reciclaje Aumentar la tasa de reciclaje de diferentes flujos es vital para asegurar la recuperación de materiales y cumplir con los compromisos adquiridos en el marco de las políticas europeas de gestión de residuos y sostenibilidad. Además, para el año 2027 la fórmula de cálculo del reciclaje considerará únicamente los biorresiduos recogidos separadamente. En materia de reciclaje, el objetivo es: Vertido Se busca limitar drásticamente la cantidad de residuos que se envían a vertederos, obligando a mejorar las recogidas selectivas y a que toda la fracción rechazo reciba un pretratamiento para poder recuperar materiales valorizables, con el objetivo de conseguir: Prevención Con la finalidad de romper el vínculo entre el crecimiento económico y los impactos sobre la salud humana y el medio ambiente asociados a la generación de residuos, las políticas de prevención de residuos se encaminan a lograr: En 2035, recoger separadamente el 50% de los residuos municipales generados.\nEn 2035, alcanzar el 65% de reciclaje de los residuos municipales en peso de los cuales el 15% debe corresponder a la preparación para la reutilización.\nEn 2035, reducir la cantidad de residuos municipales vertidos al 10% respecto a los residuos generados.\nEn 2030, una reducción del 15% en peso de los residuos generados respecto el año 2010.\nFuente: Ley 7/2022, de 8 de abril, de residuos y suelos contaminados para una economía circular. Disponible aquí.\nÁreas de desarrollo económico en la gestión de residuos municipales Este apartado se centra en los residuos municipales, en tanto que contribuyen de manera más significativa al Valor Añadido Bruto (VAB) y a la generación de empleo.\n08 Brecha en el cumplimiento de objetivos para los residuos municipales 25% 50% Objetivo 2035 Según datos del INE [+], en 2021, se recogieron de manera separada un 25% de los residuos municipales. Esta cifra es la más alta de los últimos diez años, aunque la variación anual es tan solo de 6 puntos porcentuales. El ritmo de mejora es lento, ya que esta cifra debe duplicarse, como mínimo, para el año 2035.\n100% Año 2021 Recogida separada Reciclaje Vertido Prevención 100% 65% Objetivo 2035 39% Año 2022 Según los datos provisionales de Eurostat [+] en 2022 se reciclaron el 39% de los residuos municipales generados. La distancia entre el objetivo para 2025 es de 16 puntos porcentuales y de 26 para 2035. Esta distancia supera los 40 puntos si no se contabiliza el bioestabilizado como reciclado a partir de 2027.\n0% 50% Año 2022 10% Objetivo 2035 Según los datos provisionales de Eurostat [+] en 2022 la mitad de los residuos municipales generados terminaron en vertedero. El reciente impuesto sobre el depósito de residuos en vertederos e incineración ayudará a reducir esta cifra, aunque se necesita una reducción del 80%.\nSegún los datos provisionales de Eurostat [+] entre 2010 y 2022 hubo una reducción del 6% en los residuos municipales en España. Para alcanzar los objetivos establecidos para 2025 y 2030, es necesario que en los próximos tres años la generación de residuos disminuya casi un 8% y un 10%, respectivamente.\n15% Objetivo 2030 100% Año 2022 6% 09 Principales áreas de desarrollo económico en el sector de los residuos municipales para los próximos años Recogida de residuos Recogidas separadas de alta eficiencia • Recogida separada masiva de biorresiduos • Servicios dedicados a la recogida de nuevos flujos de residuos • Nuevos modelos de recogida individualizados • Mecanismos de pago por generación o bonificación por participación • Optimización en las operaciones de recogida Infraestructura Nuevas infraestructuras para el tratamiento y la reutilización de residuos • Adaptación y modernización de las plantas de tratamiento mecánico-biológico • Construcción de nuevas plantas de reciclaje, especialmente para el tratamiento de biorresiduos • Creación de una red de centros para la preparación para la reutilización Innovación tecnológica Implementación de soluciones avanzadas • Sensorización en combinación con inteligencia artificial • Aplicación de la tecnología blockchain • Uso de drones y sistemas de monitoreo • Desarrollo del reciclaje químico • Tecnología de captura y valorización de gases Nuevas actividades Fortalecimiento del sector de la gestión de los residuos • Nuevos SCRAPs • Creación de esquemas de recuperación como los Sistemas de Depósito, Devolución y Retorno (SDDR).\n• Expansión logística de los residuos Economía circular Evolución en la cadena de valor para impulsar nuevos modelos de negocio circulares y el ecodiseño • Agentes de cambio para la economía circular a nivel sistémico • Líderes colaborativos • Consultores en materiales y reciclaje • Facilitador para el cumplimiento normativo de los productos Acciones más allá de la gestión de los residuos 10 Suponiendo que la generación de residuos municipales (RM) se reduce en un 15%, algunas cifras ayudan a valorar la magnitud del reto hasta 2030: • La recogida separada de RM debería crecer de 5,3 Mt/a en 2021 (último dato conocido) a 12,4 Mt/a en 2030.\n• La generación de fracción resto debería pasar de 16,8 Mt/a en 2021 a 8,3 Mt/a en 2030, es decir, una reducción a la mitad.\n• Se requiere dotar de nuevas instalaciones de tratamiento de biorresiduos procedentes de recogida separada para 3,5 Mt/a.\n• Se requiere dotar de nuevas instalaciones de tratamiento previo para unos 1,9 Mt/a de fracción resto.\n• La mayor parte de las plantas de triaje y de tratamiento mecánico-biológico (TMB) existentes, que trataron en 2021 más de 14 Mt/a de fracción resto, se han de actualizar para hacer frente a las necesidades de separación para el reciclado.\nLa efectividad de estas plantas resulta imprescindible para cumplir los objetivos.\n• Con la tasa del 60% de reciclaje y preparación para la reutilización, globalmente España no requiere más capacidad de incineración, aunque se puede producir combustible sólido recuperado (CSR) y valorizarlo, en lugar de verterlo como rechazo.\n• La inversión necesaria hasta 2030 se sitúa entre 3.400 y 4.900 M€. El incremento total de coste para las entidades locales (sin ayudas externas) podría superar los 1.000 M€/a.\n¿Cuáles son los costes e inversiones que la administración local debe realizar para lograr los objetivos de gestión de residuos municipales para el año 2030?\nPara alcanzar los objetivos en 2030, se requiere una inversión de entre 3.400 y 4.900 M€ además de grandes esfuerzos tecnológicos y organizativos, particularmente en recogida separada y tratamiento de biorresiduos, y en tratamiento de la fracción resto.\nRecogida y tratamiento (*) Inversión necesaria actual M€ Coste explotación M€/año Recogida separada y tratamiento de biorresiduos 2.360-3.550 410-480 Nuevo tratamiento previo de fracción resto y actualización del existente (**) 1.020-1.330 215-225 Total 3.380-4.880 650-735 (*) No incluye la valorización energética de CSR en comunidades autónomas sin acceso a la incineración (**) Incluye el nuevo impuesto de vertido y la internalización de los costes de las externalidades por emisiones de GEI en los depósitos controlados Fuente: ESGREM, 2024 11 Para que todo esto ocurra: La administración pública debe liderar la transición hacia una economía circular y la gestión sostenible de los recursos mediante la creación de un marco que alinee la inversión privada con estos objetivos.\nc c c c c c Legislar en clave circular Agilizar los procesos administrativos Fomentar la colaboración, innovación Invertir en infraestructuras y tecnologías Promover la sensibilización y educación Rendición de cuentas Crear marcos legales estables que promuevan y faciliten la adopción de prácticas circulares en todos los sectores y establezcan sistemas de incentivos, vigilancia y sanción. La disponibilidad, homogeneización, transparencia y actualización de datos es esencial para evaluar el grado de alcance de los objetivos establecidos y rendir cuentas a Europa y ante la ciudadanía. Asimismo, la transparencia económica también es necesaria.\nTransponer directrices, integrar normativas y eliminar barreras burocráticas para la obtención, por ejemplo, de la condición de fin de residuo y los permisos de autorización ambiental integrada de plantas de tratamiento de biorresiduos.\nPromover la colaboración entre actores del sector y la colaboración público-privada, fomentar la innovación y el desarrollo tecnológico en la gestión de residuos.\nDestinar recursos a la creación y mejora de infraestructuras (en especial, para el tratamiento de biorresiduos) y tecnologías que permitan alcanzar los objetivos de reciclado y de preparación para la reutilización, así como recuperar materias primas críticas.\nAumentar la conciencia pública y empresarial sobre la importancia de la economía circular. La corresponsabilización de la ciudadanía es esencial para alcanzar una recogida selectiva de calidad.\n12 Las actividades económicas con mayor aportación a la riqueza y empleo son la recogida y tratamiento de residuos no peligrosos, el comercio al por mayor de chatarra y la fabricación de productos básicos de hierro, acero y ferroaleaciones. Por otro lado, sólo los residuos municipales aportan cerca del 40% del VAB del sector.\nEl sector de los residuos se consolida como motor de crecimiento económico, con más de 41.000 millones de euros en ingresos de explotación, y una aportación del 4,9% del VAB industrial y del 7,1% de la ocupación industrial en España.\nContribución económica Composición del sector Rentabilidad y crecimiento La rentabilidad económica del sector residuos se sitúa alrededor del 5,4%, comparable con otros sectores industriales en España.\nEl sector ha mostrado un crecimiento significativo en términos de ingresos de explotación, VAB y empleo desde el año 2000, con un aumento notable especialmente a partir del año 2015.\nObjetivos claves El sector de la gestión de residuos en España se enfrenta a importantes desafíos para cumplir con los ambiciosos objetivos establecidos para 2035. Aunque se han realizado progresos en algunas áreas, las previsiones no son favorables y aún persisten brechas significativas tanto en prevención, recogida separada, reciclaje y vertido.\nEvolución y futuro Se espera que el sector continúe ampliando sus capacidades y alcance en los próximos años, impulsado por la necesidad de cumplir con los objetivos normativos.\nEl crecimiento económico del sector de la gestión de residuos está intrínsecamente ligado a la capacidad de maximizar las operaciones de captura de valor de los residuos y aprovechar las oportunidades emergentes en un contexto de transición hacia la economía circular.\nLa administración debe Liderar con visión y compromiso, facilitando el marco normativo y los recursos necesarios.\nLa transparencia en la rendición de cuentas es clave para medir el progreso de los objetivos.\n13 Conclusiones Ejecución del informe: La Fundación Fórum Ambiental es una entidad sin ánimo de lucro que tiene por objetivo crear una plataforma de diálogo y colaboración entre empresas, administraciones y el resto de la sociedad, con la finalidad de conseguir conjuntamente un modelo de desarrollo a sostenible.\nEl patronato de la Fundación Fórum Ambiental está formado por administraciones públicas y por empresas privadas, permitiendo integrar visiones complementarias y diversos ámbitos de actuación."
    },
    {
      "title": "Así gestionamos los residuos en España: Principales resultados de las ...",
      "date": "Unknown",
      "url": "https://catedraeconomiacircular-us.es/index.php?view=article&id=301:asi-gestionamos-los-residuos-en-espana-principales-resultados-de-las-estadisticas-del-ine&catid=2",
      "source": "Catedraeconomiacircular-us.es",
      "format": "Text",
      "content": "El Instituto Nacional de Estadística (INE) ha publicado su informe anual sobre la generación y gestión de residuos en España. Principales cifras del informe: Reducción del 5,4% en residuos generados en 2022 respecto a 2021. 110,1 millones de toneladas de residuos generados: 96,8% residuos no peligrosos. 3,2% residuos peligrosos. Imagen 1.",
      "raw_content": "La gestión de residuos en España: principales desafíos - waste2energy\nIr al contenido\n\n\nInicio\nPlantas de Tratamiento de Residuos\nTipos de Residuos\nResiduos Solidos Urbanos\nResiduos Orgánicos\n\n\nVentajas del Aprovechamiento de Residuos\nBlog\n\nContacto\n\n\nInicio\n\nPlantas de Tratamiento de Residuos\nTipos de Residuos\nResiduos Solidos Urbanos\nResiduos Orgánicos\n\n\nVentajas del Aprovechamiento de Residuos\nBlog\nContacto\n\nBuscar \nLa gestión de residuos en España: principales desafíos\n\nLa gestión de residuos en España es uno de los temas más relevantes en el contexto de la sostenibilidad y la protección medioambiental. Con una población de más de 48 millones de habitantes y un modelo económico que todavía depende en gran medida de la generación de residuos, el país enfrenta una situación que desafía la capacidad de las infraestructuras existentes.\nEsta problemática no sólo se traduce en dificultades operativas y logísticas, sino que también tiene repercusiones ambientales y sociales significativas, como la contaminación de suelos y aguas, y la emisión de gases de efecto invernadero provenientes de vertederos.\nEn los últimos años, la creciente presión de la Unión Europea para cumplir con los objetivos climáticos y de sostenibilidad ha impulsado a España a tomar medidas más ambiciosas.\nSin embargo, abordar estos desafíos es fundamental no sólo para cumplir con las regulaciones comunitarias, sino también para proteger la biodiversidad y garantizar la calidad de vida de las generaciones futuras.\nLa transición hacia un modelo de economía circular, que minimice los residuos y maximice la reutilización, representa una oportunidad para transformar la gestión de residuos en un motor de innovación y crecimiento económico sostenible.\nSituación actual de la gestión de residuos en España\nLa situación actual de la gestión de residuos en España es un reflejo de avances y retos persistentes.\nSegún datos recientes, el país generó 115,4 millones de toneladas de residuos en 2021, un 9,3% más que en el año anterior, lo que pone de manifiesto la magnitud del desafío.\nDe esta cifra, una parte importante todavía termina en vertederos (41,4%), lo cual es preocupante, ya que los vertederos representan una de las formas más insostenibles de gestión de residuos.\nEn comparación con otros países de la Unión Europea, España sigue teniendo una tasa de reciclaje de residuos municipales inferior, situándose en torno al 35%, mientras que la media europea se sitúa en un 47%. Una diferencia significativa que indica la necesidad de políticas más efectivas y una mejor infraestructura.\nLas políticas vigentes, como el Plan Estatal Marco de Gestión de Residuos (PEMAR 2016-2022), establecen directrices claras para reducir la dependencia de los vertederos y fomentar el reciclaje.\nUno de los principales objetivos es reducir al 35% la cantidad de residuos municipales destinados a vertederos para 2025, en cumplimiento con las normativas europeas.\nNo obstante, el progreso ha sido desigual y se ha visto ralentizado por varios factores. Uno de estos factores, por ejemplo, son las diferencias marcadas entre comunidades autónomas que complican la implementación de un sistema nacional eficiente. Regiones como Cataluña y el País Vasco han demostrado un compromiso notable con la gestión sostenible, mientras que otras zonas están rezagadas, en parte debido a la falta de recursos o inversiones en infraestructura moderna.\nAdemás, las leyes europeas, como el Paquete de Economía Circular, imponen metas cada vez más estrictas, como el objetivo de reciclar el 65% de los residuos municipales y el 75% de los residuos de envases para 2030, así como reducir el vertido a un máximo del 10% de los residuos municipales para 2035.\nEspaña se enfrenta a dificultades para adaptarse a estas exigencias dadas las carencias en instalaciones adecuadas y en innovación tecnológica en muchos municipios.\nLas inversiones públicas y privadas en el sector han sido insuficientes, lo que ha frenado la capacidad del país para modernizar las plantas de tratamiento y mejorar la logística de la recolección selectiva.\nEn conjunto, la situación actual exige una respuesta más coordinada y proactiva, que no sólo se enfoque en cumplir las normativas, sino que también promueva un cambio cultural en la forma en que se gestionan y perciben los residuos.\nPrincipales desafíos en la gestión de residuos\nUno de los mayores obstáculos en la gestión de residuos en España es el coste económico asociado.\nLa inversión necesaria para modernizar las infraestructuras de gestión de residuos se estima en miles de millones de euros. Estos costes elevados representan una carga significativa para las administraciones locales, que, a menudo, tienen que priorizar otros servicios esenciales.\nAdemás, las zonas rurales o menos desarrolladas sufren una grave carencia de instalaciones de reciclaje y tratamiento, lo que incrementa los costes logísticos al tener que transportar los residuos a largas distancias.\nEsta situación genera un efecto perjudicial en términos de sostenibilidad y emisiones, ya que el transporte intensivo contribuye al aumento de la huella de carbono.\nLa normativa actual sobre gestión de residuos en España también plantea importantes desafíos.\nA pesar de la existencia de un marco regulador europeo robusto, las leyes españolas a menudo carecen de coherencia y flexibilidad, lo que dificulta el desarrollo de soluciones innovadoras.\nLa existencia de procedimientos burocráticos complejos y lentos para obtener licencias y permisos han retrasado proyectos importantes de infraestructuras de reciclaje, limitando la capacidad del país para cumplir con los objetivos ambientales establecidos por la Unión Europea.\nEsta fragmentación regulatoria y la falta de coordinación entre las administraciones regionales y nacionales supone uno de los mayores retos a superar.\nLa participación ciudadana es también otro aspecto crítico.\nAunque las campañas de concienciación sobre la importancia del reciclaje han aumentado en los últimos años, España sigue teniendo niveles bajos de participación en comparación con otros países europeos.\nSe estima que sólo el 40% de los hogares realiza una separación efectiva de residuos, lo que dificulta alcanzar las metas de reciclaje.\nLa educación ambiental sigue siendo insuficiente, y aún existen sectores de la población que no comprenden completamente el impacto de sus hábitos de consumo en el medio ambiente.\nOportunidades y estrategias de mejora\nAnte los desafíos mencionados, la adopción de un modelo de economía circular se presenta como una solución clave.\nEste modelo busca reducir, reutilizar y reciclar materiales tanto como sea posible para minimizar el desperdicio.\nSegún las estimaciones del Parlamento Europeo, la implementación de la economía circular podría generar hasta 700,000 empleos en la UE para 2030, con un potencial significativo en España.\nLa reutilización de materiales, el diseño ecológico de productos y el fomento de mercados secundarios para productos reciclados son algunas de las estrategias clave que podrían transformar el sector.\nPor otra parte, las innovaciones tecnológicas también juegan un papel fundamental.\nTecnologías como la inteligencia artificial para la clasificación automatizada de residuos, el compostaje avanzado y el uso de big data para optimizar la logística ya se están aplicando en ciudades como Barcelona, que ha comenzado a implementar soluciones avanzadas.\nEstas innovaciones aumentan la eficiencia y reducen el impacto ambiental. Sin embargo, su adopción debe ser más amplia y apoyada por una colaboración público-privada robusta.\nEstá claro que España enfrenta desafíos económicos, normativos y sociales significativos en materia de gestión de residuos.\nLa transición hacia una economía circular y la inversión en innovaciones tecnológicas son pasos esenciales para poder superar estos obstáculos.\nSin embargo, la colaboración de todos los sectores, incluyendo la ciudadanía, también es fundamental. Lograr una gestión sostenible de residuos no sólo es una necesidad ambiental, sino también una oportunidad para transformar el futuro económico del país.\nSi necesitas información sobre cómo poder llevar a cabo la valorización de tus residuos orgánicos, contacta con nosotros para resolver tus dudas.\nAntANTERIOR\nNextSiguiente\nMÁS\nartículos\n\n\nAvances en tecnología de digestión anaerobia para tratamiento de aguas residuales\n\nLa gestión de residuos en España: principales desafíos\n\nGases renovables en la estrategia de descarbonización de España\nblog\n© Waste2energy, todos los derechos reservados.\nPolítica de Cookies\nPolítica de Privacidad\nAviso Legal\nLinkedin\ninfo@waste2energy.es\nComunidad Valenciana\nEspaña\nNewsletter\nQuiero recibir información de waste2energy,  me suscribo a sus noticias.\nHe leído y acepto la política de privacidad.\nEmail \nMe apunto\nTratamiento de datos personales\nLos datos de carácter personal proporcionados serán tratados por Waste2energy.es, como responsable de esta web.\n\nFinalidad de la recogida y tratamiento de los datos personales: enviar la información que el usuario requiera a través de la web.\nLegitimación: Consentimiento del interesado/a.\nDestinatarios: Hosting: LucusHost S.L.U. Debes saber que nuestro hosting es 100% español y 100% seguro.\nDerechos: Podrás ejercer tus derechos de acceso, rectificación, limitación y suprimir los datos en info@waste2energy.es así como el derecho a presentar una reclamación ante una autoridad de control.\n\nGestionar el consentimiento de las cookies\nPara ofrecer las mejores experiencias, utilizamos tecnologías como las cookies para almacenar y/o acceder a la información del dispositivo. El consentimiento de estas tecnologías nos permitirá procesar datos como el comportamiento de navegación o las identificaciones únicas en este sitio. No consentir o retirar el consentimiento, puede afectar negativamente a ciertas características y funciones.\nFuncional  Funcional Siempre activo\nEl almacenamiento o acceso técnico es estrictamente necesario para el propósito legítimo de permitir el uso de un servicio específico explícitamente solicitado por el abonado o usuario, o con el único propósito de llevar a cabo la transmisión de una comunicación a través de una red de comunicaciones electrónicas.\nPreferencias  Preferencias\nEl almacenamiento o acceso técnico es necesario para la finalidad legítima de almacenar preferencias no solicitadas por el abonado o usuario.\nEstadísticas  Estadísticas\nEl almacenamiento o acceso técnico que es utilizado exclusivamente con fines estadísticos. El almacenamiento o acceso técnico que se utiliza exclusivamente con fines estadísticos anónimos. Sin un requerimiento, el cumplimiento voluntario por parte de tu Proveedor de servicios de Internet, o los registros adicionales de un tercero, la información almacenada o recuperada sólo para este propósito no se puede utilizar para identificarte.\nMarketing  Marketing\nEl almacenamiento o acceso técnico es necesario para crear perfiles de usuario para enviar publicidad, o para rastrear al usuario en una web o en varias web con fines de marketing similares.\nAdministrar opciones Gestionar los servicios Gestionar {vendor_count} proveedores Leer más sobre estos propósitos\nAceptar Cookies Denegar Ver preferencias Guardar preferencias Ver preferencias\n{title} {title} {title}\nGestionar consentimiento"
    },
    {
      "title": "La gestión de residuos en España: principales desafíos",
      "date": "Unknown",
      "url": "https://waste2energy.es/desafios-gestion-residuos-en-espana/",
      "source": "Waste2energy.es",
      "format": "Text",
      "content": "Situación actual de la gestión de residuos en España. La situación actual de la gestión de residuos en España es un reflejo de avances y retos persistentes. Según datos recientes, el país generó 115,4 millones de toneladas de residuos en 2021, un 9,3% más que en el año anterior, lo que pone de manifiesto la magnitud del desafío.",
      "raw_content": "Así gestionamos los residuos en España: Principales resultados de las estadísticas del INE.\n\n\n\nInicio\nCatedra\nQuienes Somos\nContacto\n\n\nActividades\nDocencia\nI+D\nPromoción\n\n\nBiblioteca\nNoticias&Actualidad\n\n\n\nInicio\n\nCatedra\n\nQuienes Somos\nContacto\n\n\n\nActividades\n\nDocencia\nI+D\nPromoción\n\n\n\nBiblioteca\n\nNoticias&Actualidad\n\n\n\n\n\n\n\n\n\n\n\n\n\n\n\n\n   \nAsí gestionamos los residuos en España: Principales resultados de las estadísticas del INE.\nEscrito en 12 Noviembre 2024 Publicado en Uncategorised\n\nEl informe del INE proporciona información esencial para evaluar los progresos hacia una economía circular en España, lo que permite medir la presión que ejerce la actividad económica sobre el medio ambiente. Los datos se integran en la Contabilidad Medioambiental, en línea con los objetivos del Reglamento Europeo sobre estadísticas de residuos. Con esta herramienta, es posible monitorear el impacto de las políticas de reducción de residuos y promover estrategias de reciclaje y reutilización.\nEl Instituto Nacional de Estadística (INE) ha publicado su informe anual sobre la generación y gestión de residuos en España.\nPrincipales cifras del informe:\n\nReducción del 5,4% en residuos generados en 2022 respecto a 2021.\n110,1 millones de toneladas de residuos generados:\n96,8% residuos no peligrosos.\n3,2% residuos peligrosos.\n\n\nImagen 1. Residuos generados en la economía española (porcentaje). Año 2022. Fuente: Informe Residuos INE 2022\nGestión de los residuos:\n\nEl 54,7% fueron reciclados (48,9 millones de toneladas, un 0,8% menos que en 2021).\nEl 34,6% fueron depositados en\nUn 7,3% fueron reutilizados en operaciones de relleno.\nEl 3,4% fueron incinerados.\n\n\nImagen 2. Tratamiento final de residuos (porcentaje). Año 2022. Fuente: Informe Residuos INE 2022\nPrincipales fuentes de generación de residuos:\n\nConstrucción: 32,9%.\nSuministro de agua, saneamiento y gestión de residuos: 21,4%.\nHogares: 21,5%, con un incremento del 0,4% frente a 2021, dominados por residuos mezclados (79,4%).\n\nPuedes acceder a los datos detallados en la web del INE: Informe Residuos INE 2022\n\nAnterior\nSiguiente\n\n\nLa Catedra de Gestión de Residuos en la Economía Circular surge como respuesta a la importante necesidad de colaboración entre la academia y la industria para intensificar los esfuerzos en investigación, difusión y formación, para así afrontar los retos a los que se enfrenta nuestra sociedad, y más en particular el sector del medio ambiente y la gestión de residuos, para llegar a ser circular.\nLeer más\n\nCátedra de Economía Circular. Universidad de Sevilla. Escuela Técnica Superior de Ingeniería. Camino de los Descubrimientos s/n 41092 SEVILLA catedraeconomiacircular@us.es \n\n@Catedra Economia Circular - Maqueta: 2grcolor\n\n// Etiqueta Linkedin  "
    },
    {
      "title": "Producción y Gestión de Residuos en España en 2023",
      "date": "Unknown",
      "url": "https://negociosostenible.camaravalencia.com/ambiental/tendencias/produccion-y-gestion-de-residuos-en-espana-en-2023/",
      "source": "Camaravalencia.com",
      "format": "HTML",
      "content": "En 2023, la producción y gestión de residuos en España sigue siendo un desafío clave para alcanzar los objetivos de sostenibilidad y alinearse con las directrices europeas en materia de economía circular. La producción de residuos continúa aumentando debido, entre otras causas, al crecimiento de la población, la urbanización y el consumo intensivo, aunque se han implementado medidas para mejorar su gestión y reducir el impacto ambiental, aún queda mucho trabajo para conseguir ser más [...] En 2023, la producción y gestión de residuos en España sigue siendo un desafío clave para alcanzar los objetivos de sostenibilidad y alinearse con las directrices europeas en materia de economía circular. La producción de residuos continúa aumentando debido, entre otras causas, al crecimiento de la población, la urbanización y el consumo intensivo, aunque se han implementado medidas para mejorar su gestión y reducir el impacto ambiental, aún queda mucho trabajo para conseguir ser más [...] En conclusión, 2023 ha sido un año de avances en la producción y gestión de residuos en España, aunque persisten desafíos significativos. La implementación efectiva de las políticas nacionales y europeas, junto con la participación activa de ciudadanos y empresas, será crucial para alcanzar los objetivos de sostenibilidad y transformar el modelo de gestión hacia uno más eficiente y respetuoso con el medio ambiente. Es una tarea de todos.",
      "raw_content": "Portal de Sostenibilidad - Producción y Gestión de Residuos en España en 2023\n\nProducción y Gestión de Residuos en España en 2023\n\nProducción y Gestión de Residuos en España en 2023\n\nEn 2023, la producción y gestión de residuos en España sigue siendo un desafío clave para alcanzar los objetivos de sostenibilidad y alinearse con las directrices europeas en materia de economía circular. La producción de residuos continúa aumentando debido, entre otras causas, al crecimiento de la población, la urbanización y el consumo intensivo, aunque se han implementado medidas para mejorar su gestión y reducir el impacto ambiental, aún queda mucho trabajo para conseguir ser más ecoeficiente.\n\n \nProducción de Residuos en España\n \nSegún datos actualizados, España generó aproximadamente 140 millones de toneladas de residuos en 2023, incluyendo residuos municipales, industriales, agrícolas y de construcción y demolición. De esta cifra, los residuos municipales representan aproximadamente 23 millones de toneladas, lo que equivale a una media de 481 kg por habitante al año. Este dato se mantiene ligeramente por encima de la media de la Unión Europea, que ronda los 466 kg por habitante.\n \nEntre los residuos municipales, los componentes más significativos son los orgánicos (40%), plásticos (14%), papel y cartón (12%), vidrio (8%) y metales (4%). A pesar de los esfuerzos por fomentar el reciclaje, mediante la selección por materiales o fracción, el porcentaje de residuos no separados en origen sigue siendo elevado, lo que complica su tratamiento posterior.\n \nLegislación y Políticas de Gestión de residuos.\n \nEspaña está sujeta al marco normativo de la Unión Europea, incluyendo la Directiva Marco de Residuos (2008/98/CE) y las metas del Pacto Verde Europeo. En 2023, España ha avanzado en la implementación de la Ley 7/2022, de residuos y suelos contaminados para una economía circular, que busca reducir la generación de residuos y fomentar su valorización. Esta ley establece objetivos específicos, como:\n \n\nAlcanzar una tasa de reciclaje del 55% de los residuos municipales para 2025 y del 65% para 2035.\nReducir un 15% la generación de residuos en 2030 respecto a los niveles de 2010.\nProhibir la comercialización de ciertos productos plásticos de un solo uso, como cubiertos, platos y pajitas.\nAdemás, se ha reforzado el uso de instrumentos económicos como el impuesto a los vertederos y la incineración, así como el fomento del sistema de depósito, devolución y retorno (SDDR) para envases.\n\n \nInfraestructuras y Sistemas de Gestión de residuos.\nLa gestión de residuos en España se realiza mediante una combinación de sistemas públicos y privados, en la que los ayuntamientos tienen un papel crucial en los residuos municipales. En 2023, España dispone de una red de infraestructuras que incluye:\n\nPlantas de reciclaje: España cuenta con más de 200 instalaciones para el tratamiento de residuos reciclables como papel, vidrio, metales y plásticos.\nPlantas de compostaje y digestión anaerobia: Estas instalaciones tratan los residuos orgánicos para producir compost y biogás. En 2023, el 20% de los residuos orgánicos son procesados en estas plantas, una cifra que se espera aumentar con la mejora de la recogida separada.\nVertederos: Aunque los vertederos siguen siendo el destino mayoritario para los residuos (46%), su número ha disminuido debido a las políticas de reducción y cierre de vertederos no conformes.\nPlantas de valorización energética: Estas instalaciones convierten residuos no reciclables en energía, representando cerca del 12% de la gestión total.\n\n \nLogros y Retos en el Reciclaje\nEn términos de reciclaje, España ha alcanzado una tasa global del 39% para los residuos municipales en 2023. Aunque esto refleja un progreso significativo respecto a años anteriores, sigue siendo insuficiente para cumplir los objetivos de la Unión Europea.\nEl reciclaje de vidrio y papel/cartón muestra tasas superiores al 70%, mientras que los plásticos presentan cifras más bajas, en torno al 30%, debido a las dificultades técnicas y económicas de este material. Además, la recogida separada de residuos orgánicos, clave para reducir los vertederos y aumentar la producción de compost, todavía enfrenta barreras relacionadas con la sensibilización ciudadana y la falta de infraestructuras adecuadas.\n \nImpacto Ambiental y Oportunidades\nLa gestión inadecuada de residuos tiene importantes consecuencias ambientales, como la emisión de gases de efecto invernadero (GEI) provenientes de los vertederos, la contaminación de suelos y aguas, y el desperdicio de recursos valiosos. En 2023, se estima que el sector residuos contribuyó con un 3% de las emisiones totales de GEI en España.\nSin embargo, la transición hacia la economía circular presenta oportunidades significativas. El aumento del reciclaje y la valorización de residuos no solo ayuda a mitigar el cambio climático, sino que también genera empleo. En 2023, el sector de residuos empleó a más de 120.000 personas en España, con una tendencia al alza debido a la expansión de actividades relacionadas con la economía circular.\n \nPerspectivas Futuras\nPara lograr una gestión más sostenible, España debe superar varios retos, entre los que destacan:\n \n\nMejorar la recogida separada: Especialmente en el ámbito de los residuos orgánicos y plásticos, con campañas educativas y expansión de contenedores específicos.\nAumentar la inversión en infraestructuras: Plantas de reciclaje más avanzadas y tecnologías para el tratamiento de residuos complejos.\nFomentar la economía circular: Impulsar el ecodiseño, la reutilización y la reparación de productos para reducir la generación de residuos desde su origen.\nCombatir la obsolescencia programada: Con legislaciones que garanticen la durabilidad y reparabilidad de los productos.\n\n \nA modo de conclusión…..\nEn conclusión, 2023 ha sido un año de avances en la producción y gestión de residuos en España, aunque persisten desafíos significativos. La implementación efectiva de las políticas nacionales y europeas, junto con la participación activa de ciudadanos y empresas, será crucial para alcanzar los objetivos de sostenibilidad y transformar el modelo de gestión hacia uno más eficiente y respetuoso con el medio ambiente. Es una tarea de todos.\n \n \nEste artículo se ha realizado en el marco de la Resolución de IVACE+i de concesión de una subvención al Consejo de Cámaras de la Comunitat Valenciana, para el fomento de la Sostenibilidad y Desarrollo Sostenible en el año 2024.\n\nEn 2023, la producción y gestión de residuos en España sigue siendo un desafío clave para alcanzar los objetivos de sostenibilidad y alinearse con las directrices europeas en materia de economía circular. La producción de residuos continúa aumentando debido, entre otras causas, al crecimiento de la población, la urbanización y el consumo intensivo, aunque se han implementado medidas para mejorar su gestión y reducir el impacto ambiental, aún queda mucho trabajo para conseguir ser más ecoeficiente.\n\n\n\n\n\nProducción de Residuos en España\n\n\n\nSegún datos actualizados, España generó aproximadamente 140 millones de toneladas de residuos en 2023, incluyendo residuos municipales, industriales, agrícolas y de construcción y demolición. De esta cifra, los residuos municipales representan aproximadamente 23 millones de toneladas, lo que equivale a una media de 481 kg por habitante al año. Este dato se mantiene ligeramente por encima de la media de la Unión Europea, que ronda los 466 kg por habitante.\n\n\n\nEntre los residuos municipales, los componentes más significativos son los orgánicos (40%), plásticos (14%), papel y cartón (12%), vidrio (8%) y metales (4%). A pesar de los esfuerzos por fomentar el reciclaje, mediante la selección por materiales o fracción, el porcentaje de residuos no separados en origen sigue siendo elevado, lo que complica su tratamiento posterior.\n\n\n\nLegislación y Políticas de Gestión de residuos.\n\n\n\nEspaña está sujeta al marco normativo de la Unión Europea, incluyendo la Directiva Marco de Residuos (2008/98/CE) y las metas del Pacto Verde Europeo. En 2023, España ha avanzado en la implementación de la Ley 7/2022, de residuos y suelos contaminados para una economía circular, que busca reducir la generación de residuos y fomentar su valorización. Esta ley establece objetivos específicos, como:\n\n\n\n\n\nInfraestructuras y Sistemas de Gestión de residuos.\n\nLa gestión de residuos en España se realiza mediante una combinación de sistemas públicos y privados, en la que los ayuntamientos tienen un papel crucial en los residuos municipales. En 2023, España dispone de una red de infraestructuras que incluye:\n\n\n\nLogros y Retos en el Reciclaje\n\nEn términos de reciclaje, España ha alcanzado una tasa global del 39% para los residuos municipales en 2023. Aunque esto refleja un progreso significativo respecto a años anteriores, sigue siendo insuficiente para cumplir los objetivos de la Unión Europea.\n\nEl reciclaje de vidrio y papel/cartón muestra tasas superiores al 70%, mientras que los plásticos presentan cifras más bajas, en torno al 30%, debido a las dificultades técnicas y económicas de este material. Además, la recogida separada de residuos orgánicos, clave para reducir los vertederos y aumentar la producción de compost, todavía enfrenta barreras relacionadas con la sensibilización ciudadana y la falta de infraestructuras adecuadas.\n\n\n\nImpacto Ambiental y Oportunidades\n\nLa gestión inadecuada de residuos tiene importantes consecuencias ambientales, como la emisión de gases de efecto invernadero (GEI) provenientes de los vertederos, la contaminación de suelos y aguas, y el desperdicio de recursos valiosos. En 2023, se estima que el sector residuos contribuyó con un 3% de las emisiones totales de GEI en España.\n\nSin embargo, la transición hacia la economía circular presenta oportunidades significativas. El aumento del reciclaje y la valorización de residuos no solo ayuda a mitigar el cambio climático, sino que también genera empleo. En 2023, el sector de residuos empleó a más de 120.000 personas en España, con una tendencia al alza debido a la expansión de actividades relacionadas con la economía circular.\n\n\n\nPerspectivas Futuras\n\nPara lograr una gestión más sostenible, España debe superar varios retos, entre los que destacan:\n\n\n\n\n\nA modo de conclusión…..\n\nEn conclusión, 2023 ha sido un año de avances en la producción y gestión de residuos en España, aunque persisten desafíos significativos. La implementación efectiva de las políticas nacionales y europeas, junto con la participación activa de ciudadanos y empresas, será crucial para alcanzar los objetivos de sostenibilidad y transformar el modelo de gestión hacia uno más eficiente y respetuoso con el medio ambiente. Es una tarea de todos.\n\n\n\n\n\nEste artículo se ha realizado en el marco de la Resolución de IVACE+i de concesión de una subvención al Consejo de Cámaras de la Comunitat Valenciana, para el fomento de la Sostenibilidad y Desarrollo Sostenible en el año 2024.\n\nCategorías\n\nArtículos más leídos\n\nInforme Tendencias ESG 2025: Claves para la agenda empresarial de sostenibilidad | FORÉTICA\n\nInforme Tendencias ESG 2025: Claves para la agenda empresarial de sostenibilidad | FORÉTICA\n\n¿Eres un patrocinador de soluciones de sostenibilidad y quieres aparecer en este portal?\n\n¿Eres una empresa y no encuentras lo que estás buscando?\n\nSUSCRÍBETE A NUESTRA NEWSLETTER\n\nRecibe cada dos semanas todas las novedades sobre sostenibilidad empresarial.\n\n\n\nPATROCINADORES\n\nCOLABORADORES\n\nSede Central\n\nC/Poeta Querol, 15 - 46002\n\t\t\t\t\t\t\tValència Tlf. 963 103 998\n\nHorario Atención\n\nTelefónica: 9:00 a 14:00\n\t\t\t\t\t\t\tPresencial: solicitar cita previa a portaldesostenibilidad@camaravalencia.com\n\n\n\n"
    }
  ]
}